{
  "canonical_slug": "17-343-normal-minimal-wear",
  "card_type": "skin-variant",
  "exterior": "minimal-wear",
  "exterior_name": "Minimal Wear",
  "id": "17-343__normal__minimal-wear",
  "market_hash_name": "MAC-10 | Commuter (Minimal Wear)",
  "media": {
    "image_png": "data/api/media/rendered/files/skins/17-343/light.png",
    "manifest_path": "data/api/media/rendered/manifests/skin-variants/17-343__normal__minimal-wear.json",
    "preview_status": "shared-skin-render",
    "preview_tier": "light",
    "source_skin_manifest_path": "data/api/media/rendered/manifests/skins/17-343.json"
  },
  "name": "MAC-10 | Commuter (Minimal Wear)",
  "quality": "normal",
  "quality_name": "Normal",
  "search_slug": "mac-10-commuter-minimal-wear",
  "skin_id": "17-343",
  "skin_name": "MAC-10 | Commuter"
}
