{
  "canonical_slug": "36-1307-normal-minimal-wear",
  "card_type": "skin-variant",
  "exterior": "minimal-wear",
  "exterior_name": "Minimal Wear",
  "id": "36-1307__normal__minimal-wear",
  "market_hash_name": "P250 | Copper Oxide (Minimal Wear)",
  "media": {
    "image_png": "data/api/media/rendered/files/skins/36-1307/light.png",
    "manifest_path": "data/api/media/rendered/manifests/skin-variants/36-1307__normal__minimal-wear.json",
    "preview_status": "shared-skin-render",
    "preview_tier": "light",
    "source_skin_manifest_path": "data/api/media/rendered/manifests/skins/36-1307.json"
  },
  "name": "P250 | Copper Oxide (Minimal Wear)",
  "quality": "normal",
  "quality_name": "Normal",
  "search_slug": "p250-copper-oxide-minimal-wear",
  "skin_id": "36-1307",
  "skin_name": "P250 | Copper Oxide"
}
