{
  "canonical_slug": "500-411-normal-factory-new",
  "card_type": "skin-variant",
  "exterior": "factory-new",
  "exterior_name": "Factory New",
  "id": "500-411__normal__factory-new",
  "market_hash_name": "Bayonet | Damascus Steel (Factory New)",
  "media": {
    "image_png": "data/api/media/rendered/files/weapons/500/primary.png",
    "manifest_path": null,
    "preview_status": "rendered",
    "preview_tier": null,
    "source_skin_manifest_path": "data/api/media/rendered/manifests/weapons/500.json"
  },
  "name": "Bayonet | Damascus Steel (Factory New)",
  "quality": "normal",
  "quality_name": "Normal",
  "search_slug": "bayonet-damascus-steel-factory-new",
  "skin_id": "500-411",
  "skin_name": "Bayonet | Damascus Steel"
}
