{
  "display_name": "Berries And Cherries",
  "display_name_status": "localized",
  "display_name_token": "#PaintKit_aa_fade_red_blue_Tag",
  "game_id": 1002,
  "id": 1002,
  "name": "aa_fade_red_blue",
  "pattern": null,
  "rarity_ref": null,
  "resolved": {
    "description_string": "#PaintKit_aa_fade_red_blue",
    "description_tag": "#PaintKit_aa_fade_red_blue_Tag",
    "name": "aa_fade_red_blue",
    "style": "6",
    "wear_remap_max": "0.100000",
    "wear_remap_min": "0.000000"
  },
  "style_code": 6,
  "wear_max": 0.1,
  "wear_min": 0.0
}
