{
  "canonical_slug": "cu-catskulls-p90",
  "codename": "cu_catskulls_p90",
  "game_id": 156,
  "id": 156,
  "name": "Death by Kitty",
  "name_token": "#PaintKit_cu_catskulls_p90_Tag",
  "pattern": null,
  "rarity_ref": null,
  "resolved": {
    "description_string": "#PaintKit_cu_catskulls_p90",
    "description_tag": "#PaintKit_cu_catskulls_p90_Tag",
    "name": "cu_catskulls_p90",
    "style": "7",
    "use_legacy_model": "1",
    "wear_default": "0.080000",
    "wear_remap_max": "0.320000",
    "wear_remap_min": "0.080000"
  },
  "search_slug": "death-by-kitty",
  "style_code": 7,
  "wear": {
    "max_float": 0.32,
    "min_float": 0.08
  }
}
