{
  "canonical_slug": "am-nuclear-skulls3-mac10",
  "codename": "am_nuclear_skulls3_mac10",
  "game_id": 372,
  "id": 372,
  "name": "Nuclear Garden",
  "name_token": "#PaintKit_am_nuclear_skulls3_mac10_Tag",
  "pattern": null,
  "rarity_ref": null,
  "resolved": {
    "description_string": "#PaintKit_am_nuclear_skulls3_mac10",
    "description_tag": "#PaintKit_am_nuclear_skulls3_mac10_Tag",
    "name": "am_nuclear_skulls3_mac10",
    "style": "5",
    "use_legacy_model": "1",
    "wear_remap_max": "0.700000",
    "wear_remap_min": "0.000000"
  },
  "search_slug": "nuclear-garden",
  "style_code": 5,
  "wear": {
    "max_float": 0.7,
    "min_float": 0.0
  }
}
