{
  "availability": {
    "normal": true,
    "souvenir": true,
    "stattrak": false
  },
  "available_exteriors": [],
  "card_type": "weapon-skin",
  "finish": {
    "catalog_id": 17,
    "id": 17,
    "localized_names": {
      "brazilian": "Camuflagem Digital — Urbano",
      "bulgarian": "Градска разпокъсана цифрова шарка",
      "czech": "Urban DDPAT",
      "danish": "Urban DDPAT",
      "dutch": "Urban DDPAT",
      "english": "Urban DDPAT",
      "finnish": "Urbaani DDPAT",
      "french": "Urbain numérique",
      "german": "Stadt-DDPAT",
      "greek": "Urban DDPAT",
      "hungarian": "Városi DDPAT",
      "indonesian": "Urban DDPAT",
      "italian": "Urban DDPAT",
      "japanese": "Urban DDPAT",
      "koreana": "시가지 디지털 위장 무늬",
      "latam": "DDPAT urbano",
      "norwegian": "Urban DDPAT",
      "polish": "Miejski DDPAT",
      "portuguese": "Urban DDPAT",
      "romanian": "Urban DDPAT",
      "russian": "Пиксельный камуфляж «Город»",
      "schinese": "都市 DDPAT",
      "schinese_pw": "Urban DDPAT",
      "spanish": "DDPAT urbano",
      "swedish": "Urban DDPAT",
      "tchinese": "數位都市",
      "thai": "Urban DDPAT",
      "turkish": "Şehir DDPAT",
      "ukrainian": "Пікс. камуфляж «Місто»",
      "vietnamese": "Urban DDPAT"
    },
    "name": "Urban DDPAT",
    "rarity_ref": null,
    "style_code": 2,
    "style_name": "Hydrographic",
    "wear": {
      "max_float": null,
      "min_float": null
    }
  },
  "id": "17-17",
  "localized_names": {
    "brazilian": "MAC-10 | Camuflagem Digital — Urbano",
    "bulgarian": "MAC-10 | Градска разпокъсана цифрова шарка",
    "czech": "MAC-10 | Urban DDPAT",
    "danish": "MAC-10 | Urban DDPAT",
    "dutch": "MAC-10 | Urban DDPAT",
    "english": "MAC-10 | Urban DDPAT",
    "finnish": "MAC-10 | Urbaani DDPAT",
    "french": "MAC-10 | Urbain numérique",
    "german": "MAC-10 | Stadt-DDPAT",
    "greek": "MAC-10 | Urban DDPAT",
    "hungarian": "MAC-10 | Városi DDPAT",
    "indonesian": "MAC-10 | Urban DDPAT",
    "italian": "MAC-10 | Urban DDPAT",
    "japanese": "MAC-10 | Urban DDPAT",
    "koreana": "MAC-10 | 시가지 디지털 위장 무늬",
    "latam": "MAC-10 | DDPAT urbano",
    "norwegian": "MAC-10 | Urban DDPAT",
    "polish": "MAC-10 | Miejski DDPAT",
    "portuguese": "MAC-10 | Urban DDPAT",
    "romanian": "MAC-10 | Urban DDPAT",
    "russian": "MAC-10 | Пиксельный камуфляж «Город»",
    "schinese": "MAC-10 | 都市 DDPAT",
    "schinese_pw": "MAC-10 | Urban DDPAT",
    "spanish": "MAC-10 | DDPAT urbano",
    "swedish": "MAC-10 | Urban DDPAT",
    "tchinese": "MAC-10 | 數位都市",
    "thai": "MAC-10 | Urban DDPAT",
    "turkish": "MAC-10 | Şehir DDPAT",
    "ukrainian": "МАК-10 | Пікс. камуфляж «Місто»",
    "vietnamese": "MAC-10 | Urban DDPAT"
  },
  "media": {
    "asset_id": "skin__17-17",
    "images_png": [
      "data/api/media/rendered/files/skins/17-17/light.png",
      "data/api/media/rendered/files/skins/17-17/medium.png",
      "data/api/media/rendered/files/skins/17-17/heavy.png"
    ],
    "manifest_path": "data/api/media/rendered/manifests/skins/17-17.json",
    "models": [],
    "preview_images": {
      "heavy": "data/api/media/rendered/files/skins/17-17/heavy.png",
      "light": "data/api/media/rendered/files/skins/17-17/light.png",
      "medium": "data/api/media/rendered/files/skins/17-17/medium.png"
    },
    "preview_status": "rendered",
    "primary_image_png": "data/api/media/rendered/files/skins/17-17/light.png",
    "primary_preview_tier": "light",
    "source_texture_paths": {
      "heavy": "panorama/images/econ/default_generated/weapon_mac10_hy_ddpat_urb_heavy_png.vtex_c",
      "light": "panorama/images/econ/default_generated/weapon_mac10_hy_ddpat_urb_light_png.vtex_c",
      "medium": "panorama/images/econ/default_generated/weapon_mac10_hy_ddpat_urb_medium_png.vtex_c"
    }
  },
  "name": "MAC-10 | Urban DDPAT",
  "search_slug": "mac-10-urban-ddpat",
  "sources": {
    "capsules": [],
    "cases": [],
    "collections": [
      {
        "id": "set_vertigo",
        "name": "The Vertigo Collection"
      }
    ],
    "containers": [],
    "souvenir_packages": [
      {
        "flags": [],
        "id": "4666",
        "kind": "souvenir-package",
        "name": "Berlin 2019 Vertigo Souvenir Package",
        "tier": null
      }
    ]
  },
  "variant_ids": [
    "17-17__normal__vanilla",
    "17-17__souvenir__vanilla"
  ],
  "weapon": {
    "id": 17,
    "localized_names": {
      "brazilian": "MAC-10",
      "bulgarian": "MAC-10",
      "czech": "MAC-10",
      "danish": "MAC-10",
      "dutch": "MAC-10",
      "english": "MAC-10",
      "finnish": "MAC-10",
      "french": "MAC-10",
      "german": "MAC-10",
      "greek": "MAC-10",
      "hungarian": "MAC-10",
      "indonesian": "MAC-10",
      "italian": "MAC-10",
      "japanese": "MAC-10",
      "koreana": "MAC-10",
      "latam": "MAC-10",
      "norwegian": "MAC-10",
      "polish": "MAC-10",
      "portuguese": "MAC-10",
      "romanian": "MAC-10",
      "russian": "MAC-10",
      "schinese": "MAC-10",
      "schinese_pw": "MAC-10",
      "spanish": "MAC-10",
      "swedish": "MAC-10",
      "tchinese": "MAC-10",
      "thai": "MAC-10",
      "turkish": "MAC-10",
      "ukrainian": "МАК-10",
      "vietnamese": "MAC-10"
    },
    "name": "MAC-10",
    "search_slug": "mac-10",
    "weapon_group": "smg"
  },
  "wear": {
    "max_float": null,
    "min_float": null
  }
}
