{
  "items": [
    {
      "canonical_slug": "berlin2019-team-mibr",
      "card_type": "sticker",
      "group": "stickers",
      "id": "4027",
      "name": "MIBR | Berlin 2019",
      "path": "data/api/consumer/cards/stickers/4027.json",
      "search_slug": "mibr-berlin-2019"
    },
    {
      "canonical_slug": "berlin2019-team-mibr-graffiti",
      "card_type": "graffiti",
      "group": "graffiti",
      "id": "4121",
      "name": "MIBR | Berlin 2019",
      "path": "data/api/consumer/cards/graffiti/4121.json",
      "search_slug": "mibr-berlin-2019"
    }
  ],
  "key": "mibr-berlin-2019"
}
