{
  "items": [
    {
      "canonical_slug": "35-25",
      "card_type": "weapon-skin",
      "group": "skins",
      "id": "35-25",
      "name": "Nova | Forest Leaves",
      "path": "data/api/consumer/cards/skins/35-25.json",
      "search_slug": "nova-forest-leaves"
    },
    {
      "canonical_slug": "35-25-normal-vanilla",
      "card_type": "skin-variant",
      "group": "skin-variants",
      "id": "35-25__normal__vanilla",
      "name": "Nova | Forest Leaves",
      "path": "data/api/consumer/cards/skin-variants/35-25__normal__vanilla.json",
      "search_slug": "nova-forest-leaves"
    }
  ],
  "key": "nova-forest-leaves"
}
