{
  "items": [
    {
      "canonical_slug": "london2018-team-tyl",
      "card_type": "sticker",
      "group": "stickers",
      "id": "3047",
      "name": "Tyloo | London 2018",
      "path": "data/api/consumer/cards/stickers/3047.json",
      "search_slug": "tyloo-london-2018"
    },
    {
      "canonical_slug": "london2018-team-tyl-graffiti",
      "card_type": "graffiti",
      "group": "graffiti",
      "id": "3078",
      "name": "Tyloo | London 2018",
      "path": "data/api/consumer/cards/graffiti/3078.json",
      "search_slug": "tyloo-london-2018"
    }
  ],
  "key": "tyloo-london-2018"
}
