{
  "classification": {
    "association": "player",
    "finish": "Paper",
    "kind": "sticker"
  },
  "description": "This sticker was autographed by professional player Christopher Alesund playing for Ninjas in Pyjamas at Cologne 2016.\n\n50% of the proceeds from the sale of this sticker support the included players and organizations.",
  "description_token": "#StickerKit_desc_cologne2016_signature_getright",
  "display_name": "GeT_RiGhT | Cologne 2016",
  "display_name_token": "#StickerKit_cologne2016_signature_getright",
  "game_id": 1529,
  "id": 1529,
  "name": "cologne2016_signature_getright",
  "resolved": {
    "description_string": "#StickerKit_desc_cologne2016_signature_getright",
    "item_name": "#StickerKit_cologne2016_signature_getright",
    "item_rarity": "rare",
    "name": "cologne2016_signature_getright",
    "sticker_material": "cologne2016/sig_getright",
    "tournament_event_id": "10",
    "tournament_player_id": "21771190",
    "tournament_team_id": "1"
  }
}
