{
  "classification": {
    "association": "none",
    "finish": "Paper",
    "kind": "sticker"
  },
  "description": "",
  "description_token": "#StickerKit_desc_sugarface_stan",
  "display_name": "Stan",
  "display_name_token": "#StickerKit_sugarface_stan",
  "game_id": 1627,
  "id": 1627,
  "name": "sugarface_stan",
  "resolved": {
    "description_string": "#StickerKit_desc_sugarface_stan",
    "item_name": "#StickerKit_sugarface_stan",
    "item_rarity": "rare",
    "name": "sugarface_stan",
    "sticker_material": "sugarface_capsule/stan"
  }
}
