{
  "classification": {
    "association": "team",
    "finish": "Gold",
    "kind": "sticker"
  },
  "description": "",
  "description_token": "#EventItemDesc_cph2024_sticker_team",
  "display_name": "ENCE (Gold) | Copenhagen 2024",
  "display_name_token": "#StickerKit_cph2024_team_ence_gold",
  "game_id": 7293,
  "id": 7293,
  "name": "cph2024_team_ence_gold",
  "resolved": {
    "description_string": "#EventItemDesc_cph2024_sticker_team",
    "item_name": "#StickerKit_cph2024_team_ence_gold",
    "item_rarity": "ancient",
    "name": "cph2024_team_ence_gold",
    "sticker_material": "cph2024/ence_gold",
    "tournament_event_id": "22",
    "tournament_team_id": "84"
  }
}
