{
  "classification": {
    "association": "player",
    "finish": "Embroidered",
    "kind": "sticker"
  },
  "description": "This embroidered sticker was autographed by professional player Azbayar Munkhbold playing for The MongolZ at the StarLadder Budapest 2025 CS2 Major Championship.",
  "description_token": "#StickerKit_desc_bud2025_signature_senzu_embroidered",
  "display_name": "Senzu (Embroidered) | Budapest 2025",
  "display_name_token": "#StickerKit_bud2025_signature_senzu_embroidered",
  "game_id": 9727,
  "id": 9727,
  "name": "bud2025_signature_senzu_2_embroidered",
  "resolved": {
    "description_string": "#StickerKit_desc_bud2025_signature_senzu_embroidered",
    "item_name": "#StickerKit_bud2025_signature_senzu_embroidered",
    "item_rarity": "mythical",
    "name": "bud2025_signature_senzu_2_embroidered",
    "sticker_material": "bud2025/sig_senzu_embroidered",
    "tournament_event_id": "25",
    "tournament_player_id": "960454289",
    "tournament_team_id": "122"
  }
}
