{
  "items": [
    {
      "flags": [],
      "kind": "sticker",
      "sticker_id": 731,
      "tier": null
    },
    {
      "flags": [],
      "kind": "sticker",
      "sticker_id": 734,
      "tier": null
    },
    {
      "flags": [],
      "kind": "sticker",
      "sticker_id": 737,
      "tier": null
    },
    {
      "flags": [],
      "kind": "sticker",
      "sticker_id": 740,
      "tier": null
    },
    {
      "flags": [],
      "kind": "sticker",
      "sticker_id": 743,
      "tier": null
    }
  ],
  "key": "4174"
}
