{
  "items": [
    {
      "flags": [],
      "kind": "sticker",
      "sticker_id": 1400,
      "tier": null
    },
    {
      "flags": [],
      "kind": "sticker",
      "sticker_id": 1403,
      "tier": null
    },
    {
      "flags": [],
      "kind": "sticker",
      "sticker_id": 1406,
      "tier": null
    },
    {
      "flags": [],
      "kind": "sticker",
      "sticker_id": 1409,
      "tier": null
    },
    {
      "flags": [],
      "kind": "sticker",
      "sticker_id": 1412,
      "tier": null
    }
  ],
  "key": "4259"
}
