{
  "codename": "campaign magrheb",
  "entity_id": "1320",
  "entity_type": "tool",
  "id": "tool__1320",
  "name": "Campaign Maghreb",
  "refs": {
    "icon_default_image": "materials/icons/inventory_icon_campaign.vtf",
    "image_inventory": "backpack/crafting/campaign",
    "image_inventory_size": {
      "h": 82,
      "w": 128
    }
  },
  "resolved_refs": {
    "image_inventory": [
      "panorama/images/backpack/crafting/campaign_png.vtex_c"
    ]
  },
  "unresolved_refs": [
    "icon_default_image"
  ]
}
