{
  "items": [
    {
      "canonical_slug": "7-885",
      "card_type": "weapon-skin",
      "group": "skins",
      "id": "7-885",
      "name": "AK-47 | Rat Rod",
      "path": "data/api/consumer/cards/skins/7-885.json",
      "search_slug": "ak-47-rat-rod"
    },
    {
      "canonical_slug": "8-886",
      "card_type": "weapon-skin",
      "group": "skins",
      "id": "8-886",
      "name": "AUG | Arctic Wolf",
      "path": "data/api/consumer/cards/skins/8-886.json",
      "search_slug": "aug-arctic-wolf"
    },
    {
      "canonical_slug": "9-887",
      "card_type": "weapon-skin",
      "group": "skins",
      "id": "9-887",
      "name": "AWP | Containment Breach",
      "path": "data/api/consumer/cards/skins/9-887.json",
      "search_slug": "awp-containment-breach"
    },
    {
      "canonical_slug": "2-895",
      "card_type": "weapon-skin",
      "group": "skins",
      "id": "2-895",
      "name": "Dual Berettas | Balance",
      "path": "data/api/consumer/cards/skins/2-895.json",
      "search_slug": "dual-berettas-balance"
    },
    {
      "canonical_slug": "11-891",
      "card_type": "weapon-skin",
      "group": "skins",
      "id": "11-891",
      "name": "G3SG1 | Black Sand",
      "path": "data/api/consumer/cards/skins/11-891.json",
      "search_slug": "g3sg1-black-sand"
    },
    {
      "canonical_slug": "14-900",
      "card_type": "weapon-skin",
      "group": "skins",
      "id": "14-900",
      "name": "M249 | Warbird",
      "path": "data/api/consumer/cards/skins/14-900.json",
      "search_slug": "m249-warbird"
    },
    {
      "canonical_slug": "17-898",
      "card_type": "weapon-skin",
      "group": "skins",
      "id": "17-898",
      "name": "MAC-10 | Stalker",
      "path": "data/api/consumer/cards/skins/17-898.json",
      "search_slug": "mac-10-stalker"
    },
    {
      "canonical_slug": "23-888",
      "card_type": "weapon-skin",
      "group": "skins",
      "id": "23-888",
      "name": "MP5-SD | Acid Wash",
      "path": "data/api/consumer/cards/skins/23-888.json",
      "search_slug": "mp5-sd-acid-wash"
    },
    {
      "canonical_slug": "33-893",
      "card_type": "weapon-skin",
      "group": "skins",
      "id": "33-893",
      "name": "MP7 | Neon Ply",
      "path": "data/api/consumer/cards/skins/33-893.json",
      "search_slug": "mp7-neon-ply"
    },
    {
      "canonical_slug": "521-42",
      "card_type": "weapon-skin",
      "group": "skins",
      "id": "521-42",
      "name": "Nomad Knife | Blue Steel",
      "path": "data/api/consumer/cards/skins/521-42.json",
      "search_slug": "nomad-knife-blue-steel"
    },
    {
      "canonical_slug": "521-77",
      "card_type": "weapon-skin",
      "group": "skins",
      "id": "521-77",
      "name": "Nomad Knife | Boreal Forest",
      "path": "data/api/consumer/cards/skins/521-77.json",
      "search_slug": "nomad-knife-boreal-forest"
    },
    {
      "canonical_slug": "521-44",
      "card_type": "weapon-skin",
      "group": "skins",
      "id": "521-44",
      "name": "Nomad Knife | Case Hardened",
      "path": "data/api/consumer/cards/skins/521-44.json",
      "search_slug": "nomad-knife-case-hardened"
    },
    {
      "canonical_slug": "521-12",
      "card_type": "weapon-skin",
      "group": "skins",
      "id": "521-12",
      "name": "Nomad Knife | Crimson Web",
      "path": "data/api/consumer/cards/skins/521-12.json",
      "search_slug": "nomad-knife-crimson-web"
    },
    {
      "canonical_slug": "521-38",
      "card_type": "weapon-skin",
      "group": "skins",
      "id": "521-38",
      "name": "Nomad Knife | Fade",
      "path": "data/api/consumer/cards/skins/521-38.json",
      "search_slug": "nomad-knife-fade"
    },
    {
      "canonical_slug": "521-5",
      "card_type": "weapon-skin",
      "group": "skins",
      "id": "521-5",
      "name": "Nomad Knife | Forest DDPAT",
      "path": "data/api/consumer/cards/skins/521-5.json",
      "search_slug": "nomad-knife-forest-ddpat"
    },
    {
      "canonical_slug": "521-40",
      "card_type": "weapon-skin",
      "group": "skins",
      "id": "521-40",
      "name": "Nomad Knife | Night",
      "path": "data/api/consumer/cards/skins/521-40.json",
      "search_slug": "nomad-knife-night"
    },
    {
      "canonical_slug": "521-72",
      "card_type": "weapon-skin",
      "group": "skins",
      "id": "521-72",
      "name": "Nomad Knife | Safari Mesh",
      "path": "data/api/consumer/cards/skins/521-72.json",
      "search_slug": "nomad-knife-safari-mesh"
    },
    {
      "canonical_slug": "521-175",
      "card_type": "weapon-skin",
      "group": "skins",
      "id": "521-175",
      "name": "Nomad Knife | Scorched",
      "path": "data/api/consumer/cards/skins/521-175.json",
      "search_slug": "nomad-knife-scorched"
    },
    {
      "canonical_slug": "521-59",
      "card_type": "weapon-skin",
      "group": "skins",
      "id": "521-59",
      "name": "Nomad Knife | Slaughter",
      "path": "data/api/consumer/cards/skins/521-59.json",
      "search_slug": "nomad-knife-slaughter"
    },
    {
      "canonical_slug": "521-43",
      "card_type": "weapon-skin",
      "group": "skins",
      "id": "521-43",
      "name": "Nomad Knife | Stained",
      "path": "data/api/consumer/cards/skins/521-43.json",
      "search_slug": "nomad-knife-stained"
    },
    {
      "canonical_slug": "521-98",
      "card_type": "weapon-skin",
      "group": "skins",
      "id": "521-98",
      "name": "Nomad Knife | Ultraviolet",
      "path": "data/api/consumer/cards/skins/521-98.json",
      "search_slug": "nomad-knife-ultraviolet"
    },
    {
      "canonical_slug": "521-143",
      "card_type": "weapon-skin",
      "group": "skins",
      "id": "521-143",
      "name": "Nomad Knife | Urban Masked",
      "path": "data/api/consumer/cards/skins/521-143.json",
      "search_slug": "nomad-knife-urban-masked"
    },
    {
      "canonical_slug": "35-890",
      "card_type": "weapon-skin",
      "group": "skins",
      "id": "35-890",
      "name": "Nova | Plume",
      "path": "data/api/consumer/cards/skins/35-890.json",
      "search_slug": "nova-plume"
    },
    {
      "canonical_slug": "32-894",
      "card_type": "weapon-skin",
      "group": "skins",
      "id": "32-894",
      "name": "P2000 | Obsidian",
      "path": "data/api/consumer/cards/skins/32-894.json",
      "search_slug": "p2000-obsidian"
    },
    {
      "canonical_slug": "26-884",
      "card_type": "weapon-skin",
      "group": "skins",
      "id": "26-884",
      "name": "PP-Bizon | Embargo",
      "path": "data/api/consumer/cards/skins/26-884.json",
      "search_slug": "pp-bizon-embargo"
    },
    {
      "canonical_slug": "517-42",
      "card_type": "weapon-skin",
      "group": "skins",
      "id": "517-42",
      "name": "Paracord Knife | Blue Steel",
      "path": "data/api/consumer/cards/skins/517-42.json",
      "search_slug": "paracord-knife-blue-steel"
    },
    {
      "canonical_slug": "517-77",
      "card_type": "weapon-skin",
      "group": "skins",
      "id": "517-77",
      "name": "Paracord Knife | Boreal Forest",
      "path": "data/api/consumer/cards/skins/517-77.json",
      "search_slug": "paracord-knife-boreal-forest"
    },
    {
      "canonical_slug": "517-44",
      "card_type": "weapon-skin",
      "group": "skins",
      "id": "517-44",
      "name": "Paracord Knife | Case Hardened",
      "path": "data/api/consumer/cards/skins/517-44.json",
      "search_slug": "paracord-knife-case-hardened"
    },
    {
      "canonical_slug": "517-12",
      "card_type": "weapon-skin",
      "group": "skins",
      "id": "517-12",
      "name": "Paracord Knife | Crimson Web",
      "path": "data/api/consumer/cards/skins/517-12.json",
      "search_slug": "paracord-knife-crimson-web"
    },
    {
      "canonical_slug": "517-38",
      "card_type": "weapon-skin",
      "group": "skins",
      "id": "517-38",
      "name": "Paracord Knife | Fade",
      "path": "data/api/consumer/cards/skins/517-38.json",
      "search_slug": "paracord-knife-fade"
    },
    {
      "canonical_slug": "517-5",
      "card_type": "weapon-skin",
      "group": "skins",
      "id": "517-5",
      "name": "Paracord Knife | Forest DDPAT",
      "path": "data/api/consumer/cards/skins/517-5.json",
      "search_slug": "paracord-knife-forest-ddpat"
    },
    {
      "canonical_slug": "517-40",
      "card_type": "weapon-skin",
      "group": "skins",
      "id": "517-40",
      "name": "Paracord Knife | Night",
      "path": "data/api/consumer/cards/skins/517-40.json",
      "search_slug": "paracord-knife-night"
    },
    {
      "canonical_slug": "517-72",
      "card_type": "weapon-skin",
      "group": "skins",
      "id": "517-72",
      "name": "Paracord Knife | Safari Mesh",
      "path": "data/api/consumer/cards/skins/517-72.json",
      "search_slug": "paracord-knife-safari-mesh"
    },
    {
      "canonical_slug": "517-175",
      "card_type": "weapon-skin",
      "group": "skins",
      "id": "517-175",
      "name": "Paracord Knife | Scorched",
      "path": "data/api/consumer/cards/skins/517-175.json",
      "search_slug": "paracord-knife-scorched"
    },
    {
      "canonical_slug": "517-59",
      "card_type": "weapon-skin",
      "group": "skins",
      "id": "517-59",
      "name": "Paracord Knife | Slaughter",
      "path": "data/api/consumer/cards/skins/517-59.json",
      "search_slug": "paracord-knife-slaughter"
    },
    {
      "canonical_slug": "517-43",
      "card_type": "weapon-skin",
      "group": "skins",
      "id": "517-43",
      "name": "Paracord Knife | Stained",
      "path": "data/api/consumer/cards/skins/517-43.json",
      "search_slug": "paracord-knife-stained"
    },
    {
      "canonical_slug": "517-98",
      "card_type": "weapon-skin",
      "group": "skins",
      "id": "517-98",
      "name": "Paracord Knife | Ultraviolet",
      "path": "data/api/consumer/cards/skins/517-98.json",
      "search_slug": "paracord-knife-ultraviolet"
    },
    {
      "canonical_slug": "517-143",
      "card_type": "weapon-skin",
      "group": "skins",
      "id": "517-143",
      "name": "Paracord Knife | Urban Masked",
      "path": "data/api/consumer/cards/skins/517-143.json",
      "search_slug": "paracord-knife-urban-masked"
    },
    {
      "canonical_slug": "64-892",
      "card_type": "weapon-skin",
      "group": "skins",
      "id": "64-892",
      "name": "R8 Revolver | Memento",
      "path": "data/api/consumer/cards/skins/64-892.json",
      "search_slug": "r8-revolver-memento"
    },
    {
      "canonical_slug": "38-896",
      "card_type": "weapon-skin",
      "group": "skins",
      "id": "38-896",
      "name": "SCAR-20 | Torn",
      "path": "data/api/consumer/cards/skins/38-896.json",
      "search_slug": "scar-20-torn"
    },
    {
      "canonical_slug": "39-897",
      "card_type": "weapon-skin",
      "group": "skins",
      "id": "39-897",
      "name": "SG 553 | Colony IV",
      "path": "data/api/consumer/cards/skins/39-897.json",
      "search_slug": "sg-553-colony-iv"
    },
    {
      "canonical_slug": "40-899",
      "card_type": "weapon-skin",
      "group": "skins",
      "id": "40-899",
      "name": "SSG 08 | Bloodshot",
      "path": "data/api/consumer/cards/skins/40-899.json",
      "search_slug": "ssg-08-bloodshot"
    },
    {
      "canonical_slug": "525-42",
      "card_type": "weapon-skin",
      "group": "skins",
      "id": "525-42",
      "name": "Skeleton Knife | Blue Steel",
      "path": "data/api/consumer/cards/skins/525-42.json",
      "search_slug": "skeleton-knife-blue-steel"
    },
    {
      "canonical_slug": "525-77",
      "card_type": "weapon-skin",
      "group": "skins",
      "id": "525-77",
      "name": "Skeleton Knife | Boreal Forest",
      "path": "data/api/consumer/cards/skins/525-77.json",
      "search_slug": "skeleton-knife-boreal-forest"
    },
    {
      "canonical_slug": "525-44",
      "card_type": "weapon-skin",
      "group": "skins",
      "id": "525-44",
      "name": "Skeleton Knife | Case Hardened",
      "path": "data/api/consumer/cards/skins/525-44.json",
      "search_slug": "skeleton-knife-case-hardened"
    },
    {
      "canonical_slug": "525-12",
      "card_type": "weapon-skin",
      "group": "skins",
      "id": "525-12",
      "name": "Skeleton Knife | Crimson Web",
      "path": "data/api/consumer/cards/skins/525-12.json",
      "search_slug": "skeleton-knife-crimson-web"
    },
    {
      "canonical_slug": "525-38",
      "card_type": "weapon-skin",
      "group": "skins",
      "id": "525-38",
      "name": "Skeleton Knife | Fade",
      "path": "data/api/consumer/cards/skins/525-38.json",
      "search_slug": "skeleton-knife-fade"
    },
    {
      "canonical_slug": "525-5",
      "card_type": "weapon-skin",
      "group": "skins",
      "id": "525-5",
      "name": "Skeleton Knife | Forest DDPAT",
      "path": "data/api/consumer/cards/skins/525-5.json",
      "search_slug": "skeleton-knife-forest-ddpat"
    },
    {
      "canonical_slug": "525-40",
      "card_type": "weapon-skin",
      "group": "skins",
      "id": "525-40",
      "name": "Skeleton Knife | Night",
      "path": "data/api/consumer/cards/skins/525-40.json",
      "search_slug": "skeleton-knife-night"
    },
    {
      "canonical_slug": "525-72",
      "card_type": "weapon-skin",
      "group": "skins",
      "id": "525-72",
      "name": "Skeleton Knife | Safari Mesh",
      "path": "data/api/consumer/cards/skins/525-72.json",
      "search_slug": "skeleton-knife-safari-mesh"
    },
    {
      "canonical_slug": "525-175",
      "card_type": "weapon-skin",
      "group": "skins",
      "id": "525-175",
      "name": "Skeleton Knife | Scorched",
      "path": "data/api/consumer/cards/skins/525-175.json",
      "search_slug": "skeleton-knife-scorched"
    },
    {
      "canonical_slug": "525-59",
      "card_type": "weapon-skin",
      "group": "skins",
      "id": "525-59",
      "name": "Skeleton Knife | Slaughter",
      "path": "data/api/consumer/cards/skins/525-59.json",
      "search_slug": "skeleton-knife-slaughter"
    },
    {
      "canonical_slug": "525-43",
      "card_type": "weapon-skin",
      "group": "skins",
      "id": "525-43",
      "name": "Skeleton Knife | Stained",
      "path": "data/api/consumer/cards/skins/525-43.json",
      "search_slug": "skeleton-knife-stained"
    },
    {
      "canonical_slug": "525-98",
      "card_type": "weapon-skin",
      "group": "skins",
      "id": "525-98",
      "name": "Skeleton Knife | Ultraviolet",
      "path": "data/api/consumer/cards/skins/525-98.json",
      "search_slug": "skeleton-knife-ultraviolet"
    },
    {
      "canonical_slug": "525-143",
      "card_type": "weapon-skin",
      "group": "skins",
      "id": "525-143",
      "name": "Skeleton Knife | Urban Masked",
      "path": "data/api/consumer/cards/skins/525-143.json",
      "search_slug": "skeleton-knife-urban-masked"
    },
    {
      "canonical_slug": "518-42",
      "card_type": "weapon-skin",
      "group": "skins",
      "id": "518-42",
      "name": "Survival Knife | Blue Steel",
      "path": "data/api/consumer/cards/skins/518-42.json",
      "search_slug": "survival-knife-blue-steel"
    },
    {
      "canonical_slug": "518-77",
      "card_type": "weapon-skin",
      "group": "skins",
      "id": "518-77",
      "name": "Survival Knife | Boreal Forest",
      "path": "data/api/consumer/cards/skins/518-77.json",
      "search_slug": "survival-knife-boreal-forest"
    },
    {
      "canonical_slug": "518-44",
      "card_type": "weapon-skin",
      "group": "skins",
      "id": "518-44",
      "name": "Survival Knife | Case Hardened",
      "path": "data/api/consumer/cards/skins/518-44.json",
      "search_slug": "survival-knife-case-hardened"
    },
    {
      "canonical_slug": "518-12",
      "card_type": "weapon-skin",
      "group": "skins",
      "id": "518-12",
      "name": "Survival Knife | Crimson Web",
      "path": "data/api/consumer/cards/skins/518-12.json",
      "search_slug": "survival-knife-crimson-web"
    },
    {
      "canonical_slug": "518-38",
      "card_type": "weapon-skin",
      "group": "skins",
      "id": "518-38",
      "name": "Survival Knife | Fade",
      "path": "data/api/consumer/cards/skins/518-38.json",
      "search_slug": "survival-knife-fade"
    },
    {
      "canonical_slug": "518-5",
      "card_type": "weapon-skin",
      "group": "skins",
      "id": "518-5",
      "name": "Survival Knife | Forest DDPAT",
      "path": "data/api/consumer/cards/skins/518-5.json",
      "search_slug": "survival-knife-forest-ddpat"
    },
    {
      "canonical_slug": "518-40",
      "card_type": "weapon-skin",
      "group": "skins",
      "id": "518-40",
      "name": "Survival Knife | Night",
      "path": "data/api/consumer/cards/skins/518-40.json",
      "search_slug": "survival-knife-night"
    },
    {
      "canonical_slug": "518-72",
      "card_type": "weapon-skin",
      "group": "skins",
      "id": "518-72",
      "name": "Survival Knife | Safari Mesh",
      "path": "data/api/consumer/cards/skins/518-72.json",
      "search_slug": "survival-knife-safari-mesh"
    },
    {
      "canonical_slug": "518-175",
      "card_type": "weapon-skin",
      "group": "skins",
      "id": "518-175",
      "name": "Survival Knife | Scorched",
      "path": "data/api/consumer/cards/skins/518-175.json",
      "search_slug": "survival-knife-scorched"
    },
    {
      "canonical_slug": "518-59",
      "card_type": "weapon-skin",
      "group": "skins",
      "id": "518-59",
      "name": "Survival Knife | Slaughter",
      "path": "data/api/consumer/cards/skins/518-59.json",
      "search_slug": "survival-knife-slaughter"
    },
    {
      "canonical_slug": "518-43",
      "card_type": "weapon-skin",
      "group": "skins",
      "id": "518-43",
      "name": "Survival Knife | Stained",
      "path": "data/api/consumer/cards/skins/518-43.json",
      "search_slug": "survival-knife-stained"
    },
    {
      "canonical_slug": "518-98",
      "card_type": "weapon-skin",
      "group": "skins",
      "id": "518-98",
      "name": "Survival Knife | Ultraviolet",
      "path": "data/api/consumer/cards/skins/518-98.json",
      "search_slug": "survival-knife-ultraviolet"
    },
    {
      "canonical_slug": "518-143",
      "card_type": "weapon-skin",
      "group": "skins",
      "id": "518-143",
      "name": "Survival Knife | Urban Masked",
      "path": "data/api/consumer/cards/skins/518-143.json",
      "search_slug": "survival-knife-urban-masked"
    },
    {
      "canonical_slug": "30-889",
      "card_type": "weapon-skin",
      "group": "skins",
      "id": "30-889",
      "name": "Tec-9 | Decimator",
      "path": "data/api/consumer/cards/skins/30-889.json",
      "search_slug": "tec-9-decimator"
    }
  ],
  "key": "4620"
}
