{
  "association": "player",
  "canonical_slug": "berlin2019-signature-kinqie",
  "card_type": "sticker",
  "description": "This sticker was autographed by professional player Semyon Lisitsyn playing for DreamEaters at Berlin 2019.",
  "finish": "Paper",
  "id": 4477,
  "localized_names": {
    "english": "kinqie | Berlin 2019"
  },
  "media": {
    "asset_id": "sticker__4477",
    "images": [
      "panorama/images/econ/stickers/berlin2019/sig_kinqie_png.vtex_c",
      "panorama/images/econ/stickers/berlin2019/sig_kinqie_1355_37_png.vtex_c"
    ],
    "images_png": [
      "data/api/media/rendered/files/stickers/4477/primary.png"
    ],
    "manifest_path": "data/api/media/rendered/manifests/stickers/4477.json",
    "models": [],
    "preview_status": "rendered",
    "primary_image_png": "data/api/media/rendered/files/stickers/4477/primary.png",
    "source_texture_path": "panorama/images/econ/stickers/berlin2019/sig_kinqie_png.vtex_c"
  },
  "name": "kinqie | Berlin 2019",
  "player_id": 42106423,
  "rarity_ref": "rare",
  "search_slug": "kinqie-berlin-2019",
  "team_id": 93,
  "tournament_event_id": 16
}
