{
  "association": "player",
  "canonical_slug": "sha2024-signature-fame-1-holo",
  "card_type": "sticker",
  "description": "This holographic sticker was autographed by professional player Petr Bolyshev playing for Virtus.Pro at the Perfect World Shanghai 2024 CS2 Major Championship.",
  "finish": "Holo",
  "id": 8243,
  "localized_names": {
    "english": "fame (Holo) | Shanghai 2024"
  },
  "media": {
    "asset_id": "sticker__8243",
    "coverage_status": "rendered",
    "images": [
      "panorama/images/econ/stickers/sha2024/sig_fame_holo_png.vtex_c",
      "panorama/images/econ/stickers/sha2024/sig_fame_holo_1355_37_png.vtex_c"
    ],
    "images_png": [
      "data/api/media/rendered/files/stickers/8243/primary.png"
    ],
    "manifest_path": "data/api/media/rendered/manifests/stickers/8243.json",
    "media_scope": "rendered-entity",
    "models": [],
    "preview_status": "rendered",
    "primary_image_png": "data/api/media/rendered/files/stickers/8243/primary.png",
    "source_texture_path": "panorama/images/econ/stickers/sha2024/sig_fame_holo_png.vtex_c"
  },
  "name": "fame (Holo) | Shanghai 2024",
  "player_id": 119848818,
  "rarity": {
    "color_ref": "desc_legendary",
    "id": "legendary",
    "localized_names": {
      "brazilian": "Secreto",
      "bulgarian": "Класифицирано оръжие",
      "czech": "Tajná",
      "danish": "Klassificeret",
      "dutch": "Geheim",
      "english": "Classified",
      "finnish": "Luottamuksellinen",
      "french": "Classifiée",
      "german": "Vertraulich",
      "greek": "Classified",
      "hungarian": "Bizalmas",
      "indonesian": "Rahasia",
      "italian": "Confidenziale",
      "japanese": "機密",
      "koreana": "기밀",
      "latam": "de tipo clasificado",
      "norwegian": "Klassifisert",
      "polish": "klasy „poufne”",
      "portuguese": "Confidencial",
      "romanian": "Secret(ă)",
      "russian": "Засекреченное",
      "schinese": "保密级",
      "schinese_pw": "Classified",
      "spanish": "de tipo clasificado",
      "swedish": "Sekretessbelagd",
      "tchinese": "機密",
      "thai": "ลับเฉพาะ",
      "turkish": "Gizli",
      "ukrainian": "секретна зброя",
      "vietnamese": "Hạng tuyệt mật"
    },
    "name": "Classified",
    "source": "rarity-ref",
    "value": "5"
  },
  "rarity_ref": "legendary",
  "search_slug": "fame-holo-shanghai-2024",
  "team_id": 31,
  "tournament_event_id": 23
}
