{
  "association": "team",
  "codename": "atlanta2017_team_fntc",
  "description": "50% of the proceeds from the sale of this sticker support the included players and organizations.",
  "finish": "Paper",
  "game_id": 1754,
  "id": 1754,
  "kind": "sticker",
  "material": "atlanta2017/fntc",
  "name": "Fnatic | Atlanta 2017",
  "player_id": null,
  "player_name": null,
  "rarity_ref": "rare",
  "search_slug": "fnatic-atlanta-2017",
  "team_id": 6,
  "team_name": "Fntc",
  "tournament_event_id": 11
}
