{
  "association": "player",
  "codename": "berlin2019_signature_nealan",
  "description": "This sticker was autographed by professional player Sanzhar Iskhakov playing for Syman Gaming at Berlin 2019.",
  "finish": "Paper",
  "game_id": 4447,
  "id": 4447,
  "kind": "sticker",
  "material": "berlin2019/sig_nealan",
  "name": "neaLaN | Berlin 2019",
  "player_id": 93777050,
  "player_name": "neaLaN",
  "rarity_ref": "rare",
  "search_slug": "nealan-berlin-2019",
  "team_id": 92,
  "team_name": "SYMA",
  "tournament_event_id": 16
}
