{
  "association": "player",
  "codename": "cph2024_signature_karrigan_2",
  "description": "This sticker was autographed by professional player Finn Andersen playing for FaZe Clan at the PGL Copenhagen 2024 CS2 Major Championship.",
  "finish": "Paper",
  "game_id": 7447,
  "id": 7447,
  "kind": "sticker",
  "material": "cph2024/sig_karrigan",
  "name": "karrigan | Copenhagen 2024",
  "player_id": 29164525,
  "player_name": "karrigan",
  "rarity_ref": "rare",
  "search_slug": "karrigan-copenhagen-2024",
  "team_id": 61,
  "team_name": "FAZE",
  "tournament_event_id": 22
}
