{
  "association": "player",
  "codename": "sha2024_signature_ultimate_1",
  "description": "This sticker was autographed by professional player Roland Tomkowiak playing for Team Liquid at the Perfect World Shanghai 2024 CS2 Major Championship.",
  "finish": "Paper",
  "game_id": 8257,
  "id": 8257,
  "kind": "sticker",
  "material": "sha2024/sig_ultimate",
  "name": "ultimate | Shanghai 2024",
  "player_id": 323723495,
  "player_name": "ultimate",
  "rarity_ref": "rare",
  "search_slug": "ultimate-shanghai-2024",
  "team_id": 48,
  "team_name": "LIQ",
  "tournament_event_id": 23
}
