{
  "association": "player",
  "canonical_slug": "aus2025-signature-cool4st-4-gold",
  "codename": "aus2025_signature_cool4st_4_gold",
  "description": "This gold sticker was autographed by professional player Sodbileg Batbaatar playing for Chinggis Warriors at the BLAST.tv Austin 2025 CS2 Major Championship.",
  "finish": "Gold",
  "game_id": 9318,
  "id": 9318,
  "kind": "sticker",
  "material": "aus2025/sig_cool4st_gold",
  "name": "cool4st (Gold) | Austin 2025",
  "player_id": 882582488,
  "player_name": "cool4st",
  "rarity_ref": "ancient",
  "search_slug": "cool4st-gold-austin-2025",
  "team_id": 138,
  "team_name": "CHIN",
  "tournament_event_id": 24
}
