{
  "items": [
    {
      "id": "515-415__stattrak__minimal-wear",
      "kind": "skin-variant"
    },
    {
      "id": "515-416__stattrak__minimal-wear",
      "kind": "skin-variant"
    },
    {
      "id": "515-417__stattrak__minimal-wear",
      "kind": "skin-variant"
    },
    {
      "id": "515-418__stattrak__minimal-wear",
      "kind": "skin-variant"
    },
    {
      "id": "515-419__stattrak__minimal-wear",
      "kind": "skin-variant"
    },
    {
      "id": "515-420__stattrak__minimal-wear",
      "kind": "skin-variant"
    },
    {
      "id": "515-421__stattrak__minimal-wear",
      "kind": "skin-variant"
    }
  ],
  "key": "StatTrak™ Butterfly Knife | Doppler (Minimal Wear)"
}
